odoo/addons/ddmrp_chatter/README.rst
odoo/addons/ddmrp_chatter/__init__.py
odoo/addons/ddmrp_chatter/__manifest__.py
odoo/addons/ddmrp_chatter/i18n/ddmrp_chatter.pot
odoo/addons/ddmrp_chatter/i18n/es.po
odoo/addons/ddmrp_chatter/i18n/it.po
odoo/addons/ddmrp_chatter/models/__init__.py
odoo/addons/ddmrp_chatter/models/stock_buffer.py
odoo/addons/ddmrp_chatter/readme/CONTRIBUTORS.md
odoo/addons/ddmrp_chatter/readme/DESCRIPTION.md
odoo/addons/ddmrp_chatter/readme/HISTORY.md
odoo/addons/ddmrp_chatter/static/description/icon.png
odoo/addons/ddmrp_chatter/static/description/index.html
odoo/addons/ddmrp_chatter/views/ddmrp_buffer_view.xml
odoo_addon_ddmrp_chatter-18.0.1.0.0.3.dist-info/METADATA
odoo_addon_ddmrp_chatter-18.0.1.0.0.3.dist-info/WHEEL
odoo_addon_ddmrp_chatter-18.0.1.0.0.3.dist-info/top_level.txt
odoo_addon_ddmrp_chatter-18.0.1.0.0.3.dist-info/RECORD
